CHANGELOG.txt
LICENCE.txt
MANIFEST.in
README.txt
setup.py
DextroSort/__init__.py
dextrosort.egg-info/PKG-INFO
dextrosort.egg-info/SOURCES.txt
dextrosort.egg-info/dependency_links.txt
dextrosort.egg-info/top_level.txt