Metadata-Version: 2.1
Name: dextrosort
Version: 0.0.1
Summary: A simple and efficient merge sort implementation using divide-and-conquer.
Home-page: UNKNOWN
Author: M Vashishta Varma
Author-email: levovarma@gmail.com
License: MIT
Keywords: dextrosort
Platform: UNKNOWN
Classifier: Development Status :: 3 - Alpha
Classifier: Intended Audience :: Education
Classifier: Programming Language :: Python :: 3
Classifier: License :: OSI Approved :: MIT License
Classifier: Operating System :: OS Independent
Classifier: Topic :: Education
Classifier: Topic :: Software Development :: Libraries :: Python Modules
Requires-Python: >=3.6
License-File: LICENCE.txt
